{
  "_class": "symbolInstance",
  "booleanOperation": -1,
  "clippingMaskMode": 0,
  "do_objectID": "F3671847-EFD5-4AC4-B9F1-808BF601223B",
  "exportOptions": {
    "_class": "exportOptions",
    "do_objectID": "A626EC56-1C19-4525-87C9-F12F1F885868",
    "exportFormats": [
      {
        "_class": "exportFormat",
        "absoluteSize": 0,
        "fileFormat": "png",
        "name": "",
        "namingScheme": 0,
        "scale": 1,
        "visibleScaleType": 0
      },
      {
        "_class": "exportFormat",
        "absoluteSize": 0,
        "fileFormat": "png",
        "name": "@2x",
        "namingScheme": 0,
        "scale": 2,
        "visibleScaleType": 0
      },
      {
        "_class": "exportFormat",
        "absoluteSize": 0,
        "fileFormat": "png",
        "name": "@3x",
        "namingScheme": 0,
        "scale": 3,
        "visibleScaleType": 0
      }
    ],
    "includedLayerIds": [
    ],
    "layerOptions": 0,
    "shouldTrim": false
  },
  "frame": {
    "_class": "rect",
    "constrainProportions": false,
    "do_objectID": "3C0A4967-AEAD-4471-A3D4-E2A590677B30",
    "height": 48,
    "width": 375,
    "x": 0,
    "y": 68
  },
  "hasClippingMask": false,
  "horizontalSpacing": 0,
  "isFixedToViewport": false,
  "isFlippedHorizontal": false,
  "isFlippedVertical": false,
  "isLocked": false,
  "isVisible": true,
  "layerListExpandedType": 0,
  "name": "tab / headerBottomThird",
  "nameIsFixed": true,
  "overrideValues": [
    {
      "_class": "overrideValue",
      "do_objectID": "DAEF523B-BD2F-4A54-B6E5-C7ABEE876F59",
      "overrideName": "FC5B476F-552C-465C-8BDA-34BCFFF98A96/E3F501D7-7B9C-4271-81C4-48173FB53BEE_stringValue",
      "value": "Winnings"
    },
    {
      "_class": "overrideValue",
      "do_objectID": "5D864DF6-FB64-4856-B055-1D627C6171AA",
      "overrideName": "5DAA7C59-D02C-40EE-98D9-5C739FF3536A/7696BC26-1977-460D-A92B-8216E2450AF3_stringValue",
      "value": "Live Prize"
    },
    {
      "_class": "overrideValue",
      "do_objectID": "B3513F6D-4E1A-4436-A7A2-5BDFB73A4AC4",
      "overrideName": "8C080F75-19F6-4E84-A2F5-1BB818A24545/E3F501D7-7B9C-4271-81C4-48173FB53BEE_stringValue",
      "value": "Finished"
    }
  ],
  "resizingConstraint": 63,
  "resizingType": 0,
  "rotation": 0,
  "scale": 1,
  "shouldBreakMaskChain": false,
  "style": {
    "_class": "style",
    "do_objectID": "1A0D45C5-897F-492B-A9B6-39A9486EDE32",
    "endMarkerType": 0,
    "miterLimit": 10,
    "startMarkerType": 0,
    "windingRule": 1
  },
  "symbolID": "A88812F4-EF5D-4F84-9269-390338299CF7",
  "verticalSpacing": 0
}