{
  "_class": "symbolInstance",
  "booleanOperation": -1,
  "clippingMaskMode": 0,
  "do_objectID": "03651B4B-1858-42CF-A0FA-D99AEC5E438F",
  "exportOptions": {
    "_class": "exportOptions",
    "do_objectID": "7A6C92BE-52CD-4777-9939-9258FD9A9A36",
    "exportFormats": [
      {
        "_class": "exportFormat",
        "absoluteSize": 0,
        "fileFormat": "png",
        "name": "",
        "namingScheme": 0,
        "scale": 1,
        "visibleScaleType": 0
      },
      {
        "_class": "exportFormat",
        "absoluteSize": 0,
        "fileFormat": "png",
        "name": "@2x",
        "namingScheme": 0,
        "scale": 2,
        "visibleScaleType": 0
      },
      {
        "_class": "exportFormat",
        "absoluteSize": 0,
        "fileFormat": "png",
        "name": "@3x",
        "namingScheme": 0,
        "scale": 3,
        "visibleScaleType": 0
      }
    ],
    "includedLayerIds": [
    ],
    "layerOptions": 0,
    "shouldTrim": false
  },
  "frame": {
    "_class": "rect",
    "constrainProportions": false,
    "do_objectID": "7A8DECAE-C792-4066-A2B3-8E0FBFE48244",
    "height": 48,
    "width": 375,
    "x": 0,
    "y": 59
  },
  "hasClippingMask": false,
  "horizontalSpacing": 0,
  "isFixedToViewport": false,
  "isFlippedHorizontal": false,
  "isFlippedVertical": false,
  "isLocked": false,
  "isVisible": true,
  "layerListExpandedType": 0,
  "name": "list / header",
  "nameIsFixed": false,
  "overrideValues": [
    {
      "_class": "overrideValue",
      "do_objectID": "50D8791B-DC9B-4EB7-9DD1-1DCCEE361A94",
      "overrideName": "4C063D82-1393-42EC-B63F-5149B1DDC0CE_stringValue",
      "value": "Recommendation"
    },
    {
      "_class": "overrideValue",
      "do_objectID": "FFAFC1D5-97CA-4C95-B0D3-7C8B0D8DC84B",
      "overrideName": "946B5CD3-4429-40DE-BC55-4AB87646C00C_symbolID",
      "value": ""
    },
    {
      "_class": "overrideValue",
      "do_objectID": "D85EF782-69BE-4C13-896E-4D106A5A2306",
      "overrideName": "3BF157FB-E04F-4DE5-AFDC-63D5DCAE7A25_symbolID",
      "value": ""
    },
    {
      "_class": "overrideValue",
      "do_objectID": "C7422598-D7E3-4515-B8E2-B064E493BFF5",
      "overrideName": "C46058B6-3FBC-42F1-AFDE-8EFFE03F8FA3_symbolID",
      "value": ""
    }
  ],
  "resizingConstraint": 13,
  "resizingType": 0,
  "rotation": 0,
  "scale": 1,
  "shouldBreakMaskChain": false,
  "style": {
    "_class": "style",
    "do_objectID": "7D300EAC-3B58-45E1-91A7-DEA15B2C682A",
    "endMarkerType": 0,
    "miterLimit": 10,
    "startMarkerType": 0,
    "windingRule": 1
  },
  "symbolID": "EC301A86-FD96-40B1-A9AB-7016712B705C",
  "verticalSpacing": 0
}