{
  "_class": "symbolInstance",
  "booleanOperation": -1,
  "clippingMaskMode": 0,
  "do_objectID": "ADBCC32D-253C-47A7-853D-3D6D368CB481",
  "exportOptions": {
    "_class": "exportOptions",
    "do_objectID": "88991217-BCAB-4427-A04F-D4BCDBE695B3",
    "exportFormats": [
      {
        "_class": "exportFormat",
        "absoluteSize": 0,
        "fileFormat": "png",
        "name": "",
        "namingScheme": 0,
        "scale": 1,
        "visibleScaleType": 0
      },
      {
        "_class": "exportFormat",
        "absoluteSize": 0,
        "fileFormat": "png",
        "name": "@2x",
        "namingScheme": 0,
        "scale": 2,
        "visibleScaleType": 0
      },
      {
        "_class": "exportFormat",
        "absoluteSize": 0,
        "fileFormat": "png",
        "name": "@3x",
        "namingScheme": 0,
        "scale": 3,
        "visibleScaleType": 0
      }
    ],
    "includedLayerIds": [
    ],
    "layerOptions": 0,
    "shouldTrim": false
  },
  "frame": {
    "_class": "rect",
    "constrainProportions": false,
    "do_objectID": "987BBC47-EB11-4D26-BF98-E00B1AE5938E",
    "height": 48,
    "width": 48,
    "x": 327,
    "y": 0
  },
  "hasClippingMask": false,
  "horizontalSpacing": 0,
  "isFixedToViewport": false,
  "isFlippedHorizontal": false,
  "isFlippedVertical": false,
  "isLocked": false,
  "isVisible": true,
  "layerListExpandedType": 0,
  "name": "bound / 48",
  "nameIsFixed": false,
  "overrideValues": [
    {
      "_class": "overrideValue",
      "do_objectID": "33F0AD8F-D3EF-40D5-B75A-036BCDD2234D",
      "overrideName": "0D5AC57A-37C5-4124-B3C0-CC07FAD3938F_symbolID",
      "value": "399920FB-7E1A-41C5-9578-7366B5B48900"
    }
  ],
  "resizingConstraint": 12,
  "resizingType": 0,
  "rotation": 0,
  "scale": 1,
  "shouldBreakMaskChain": false,
  "style": {
    "_class": "style",
    "do_objectID": "46B28CF1-4908-4E42-96D7-93C2A31A0839",
    "endMarkerType": 0,
    "miterLimit": 10,
    "startMarkerType": 0,
    "windingRule": 1
  },
  "symbolID": "FF8B0A74-F8BA-4E47-B275-D7C05CF7C00C",
  "verticalSpacing": 0
}